aws/__init__.py
aws/aws_dataprocessing_mcp_server/__init__.py
aws/aws_dataprocessing_mcp_server/main.py
aws_aws_dataprocessing_mcp_server-0.1.1.dist-info/METADATA
aws_aws_dataprocessing_mcp_server-0.1.1.dist-info/WHEEL
aws_aws_dataprocessing_mcp_server-0.1.1.dist-info/entry_points.txt
aws_aws_dataprocessing_mcp_server-0.1.1.dist-info/top_level.txt
aws_aws_dataprocessing_mcp_server-0.1.1.dist-info/RECORD
