Metadata-Version: 2.4
Name: aws.aws-dataprocessing-mcp-server
Version: 0.1.1
Summary: A package that creates a file in the home directory upon installation
Home-page: https://github.com/yourusername/aws-dataprocessing-mcp-server
Author: Your Name
Author-email: your.email@example.com
Classifier: Programming Language :: Python :: 3
Classifier: License :: OSI Approved :: MIT License
Classifier: Operating System :: OS Independent
Requires-Python: >=3.6
Dynamic: author
Dynamic: author-email
Dynamic: classifier
Dynamic: description
Dynamic: description-content-type
Dynamic: home-page
Dynamic: requires-python
Dynamic: summary
